vidcrawler/Dockerfile
vidcrawler/__init__.py
vidcrawler/bitchute.py
vidcrawler/brighteon.py
vidcrawler/brighteon_bot.py
vidcrawler/cli_fetch_rumble_channel.py
vidcrawler/cmd.py
vidcrawler/date.py
vidcrawler/downloadmp3.py
vidcrawler/error.py
vidcrawler/fetch_html.py
vidcrawler/gabtv.py
vidcrawler/generic_downloader.py
vidcrawler/io.py
vidcrawler/library.py
vidcrawler/odysee.py
vidcrawler/playwright_launcher.py
vidcrawler/rumble.py
vidcrawler/rumble_bot.py
vidcrawler/run_tests.py
vidcrawler/spider.py
vidcrawler/spotify.py
vidcrawler/spreaker.py
vidcrawler/types.py
vidcrawler/video_info.py
vidcrawler/youtube.py
vidcrawler/youtube_bot.py
vidcrawler/youtube_pull.py
vidcrawler/ytdlp.py
vidcrawler/testing/__init__.py
vidcrawler/testing/simple_http_server.py
vidcrawler/testing/test_bad_video.py
vidcrawler/testing/test_cmd.py
vidcrawler/testing/test_generic_downloader.py
vidcrawler/testing/test_io.py
vidcrawler/testing/test_playwright.py
vidcrawler/testing/test_scraper_bitchute.py
vidcrawler/testing/test_scraper_brighteon.py
vidcrawler/testing/test_scraper_gabtv.py
vidcrawler/testing/test_scraper_odysee.py
vidcrawler/testing/test_scraper_rumble.py
vidcrawler/testing/test_scraper_spotify.py
vidcrawler/testing/test_scraper_spreaker.py
vidcrawler/testing/test_scraper_youtube.py
vidcrawler/testing/test_videoinfo.py
vidcrawler/testing/test_youtube_bot.py
vidcrawler-1.0.49.dist-info/LICENSE
vidcrawler-1.0.49.dist-info/METADATA
vidcrawler-1.0.49.dist-info/WHEEL
vidcrawler-1.0.49.dist-info/entry_points.txt
vidcrawler-1.0.49.dist-info/top_level.txt
vidcrawler-1.0.49.dist-info/RECORD
