Metadata-Version: 2.2
Name: vidcrawler
Version: 1.0.49
Summary: Video Crawler
Home-page: https://github.com/zackees/vidcrawler
Author: Zach Vorhies
Author-email: dont@email.me
License: MIT
Requires-Python: >=3.10
License-File: LICENSE
Requires-Dist: feedparser
Requires-Dist: pytz
Requires-Dist: beautifulsoup4>=4.13.3
Requires-Dist: keyvalue_sqlite
Requires-Dist: python-dateutil
Requires-Dist: isodate
Requires-Dist: requests
Requires-Dist: types-python-dateutil
Requires-Dist: types-pytz
Requires-Dist: types-requests
Requires-Dist: filelock
Requires-Dist: static-ffmpeg
Requires-Dist: pytest-playwright
Requires-Dist: ytdlp-brighteon>=2023.10.3
Requires-Dist: docker-run-cmd>=1.0.13
Requires-Dist: Pillow
Requires-Dist: certifi
Requires-Dist: appdirs
Requires-Dist: open-webdriver>=1.5.0
Provides-Extra: full
Requires-Dist: open-webdriver>=1.5.0; extra == "full"
Requires-Dist: yt-dlp>=2025.1.26; extra == "full"
Dynamic: author
Dynamic: author-email
Dynamic: home-page
